deeplocalizer/__init__.py
deeplocalizer/deeplocalizer.py
deeplocalizer-0.0.3.dist-info/METADATA
deeplocalizer-0.0.3.dist-info/WHEEL
deeplocalizer-0.0.3.dist-info/top_level.txt
deeplocalizer-0.0.3.dist-info/RECORD
