Metadata-Version: 2.2
Name: deeplocalizer
Version: 0.0.3
Summary: Package to localize torch deep learning models
Requires-Python: >=3.10
Requires-Dist: matplotlib>=3.10.1
Requires-Dist: numpy<2
Requires-Dist: pandas>=2.2.3
Requires-Dist: pyarrow>=19.0.1
Requires-Dist: safetensors>=0.5.3
Requires-Dist: seaborn>=0.13.2
Requires-Dist: torch==2.2.0
Requires-Dist: tqdm>=4.67.1
